{
    "root": "C:\\Users\\Arman\\Projects\\bots\\discord\\vandaire\\assets\\",

    "files": {
        "china": "china.mp3",
        "bigchina": "bigchina.mp3",
        "fired": "fired.mp3",
        "pussy": "pussy.mp3",
        "bomb": "bomb.mp3",
        "trumptrumptrump": "trumptrumptrump.mp3",
        "failed": "failed.mp3",
        "aloser": "aloser.mp3",
        "wrong": "wrong.mp3",
        "lowenergy": "lowenergy.mp3",
        "tedcruz": "tedcruz.mp3",
        "barackobama": "barackobama.mp3",
        "hillary": "hillary.mp3",
        "jebbush": "jebbush.mp3",
        "bullshit": "bullshit.mp3",
        "garbage": "garbage.mp3",
        "insecure-guy": "insecure-guy.mp3",
        "whatamisaying": "whatamisaying.mp3",
        "killers": "killers.mp3",
        "english": "english.mp3",
        "ilovechina": "ilovechina.mp3",
        "tellit": "tellit.mp3",
        "captured": "captured.mp3",
        "freetrader": "freetrader.mp3",
        "noaction": "noaction.mp3",
        "stupidpeople": "stupidpeople.mp3",
        "traitor": "traitor.mp3",
        "oyaye": "oyaye.mp3",
        "nobush": "nobush.mp3",
        "lowenergy2": "lowenergy2.mp3",
        "hardtime": "hardtime.mp3",
        "problem": "problem.mp3",
        "stupidity": "stupidity.mp3",
        "idontcare": "idontcare.mp3",
        "mexicanpeople": "mexicanpeople.mp3",
        "coats": "coats.mp3",
        "wall": "wall.mp3",
        "nasty2": "nasty2.mp3",
        "losers": "losers.mp3",
        "rich": "rich.mp3",
        "saudis": "saudis.mp3",
        "holdit": "holdit.mp3",
        "sitdown": "sitdown.mp3",
        "believeme": "believeme.mp3",
        "univision": "univision.mp3",
        "bequietandjusthitthem": "bequietandjusthitthem.mp3",
        "bingbong": "bingbong.mp3",
        "countrygoingtohell": "countrygoingtohell.mp3",
        "debtking": "debtking.mp3",
        "dontremember": "dontremember.mp3",
        "gethimout": "gethimout.mp3",
        "gettingridofobamacare": "gettingridofobamacare.mp3",
        "heardofivanka": "heardofivanka.mp3",
        "hombres": "hombres.mp3",
        "i_congrats": "i_congrats.mp3",
        "i_country_in_trouble": "i_country_in_trouble.mp3",
        "i_just_want_them_to_suffer": "i_just_want_them_to_suffer.mp3",
        "iloveyou": "iloveyou.mp3",
        "ive_been_watching_you_for_the_last_couple_of_weeks": "ive_been_watching_you_for_the_last_couple_of_weeks.mp3",
        "letsdoit": "letsdoit.mp3",
        "listentothis": "listentothis.mp3",
        "manymillions": "manymillions.mp3",
        "mn_love_my_life": "mn_love_my_life.mp3",
        "mn_employ_people": "mn_employ_people.mp3",
        "milliondollars": "milliondollars.mp3"
    }
}